Metadata-Version: 2.1
Name: live-agent
Version: 0.11.1
Summary: A framework for implementing agents which interact with the Intelie LIVE platform
Home-page: https://github.com/intelie/live-agent
Author: Vitor Mazzi
Author-email: vitor.mazzi@intelie.com.br
License: UNKNOWN
Platform: UNKNOWN
Classifier: Programming Language :: Python :: 3
Classifier: License :: OSI Approved :: GNU General Public License v3 (GPLv3)
Classifier: Operating System :: POSIX :: Linux
Classifier: Development Status :: 4 - Beta
Classifier: Topic :: Software Development :: Libraries :: Application Frameworks
Requires-Python: >=3.7
Provides-Extra: chatbot
Provides-Extra: las
